EventBusClient/EventBusClient.pdf
EventBusClient/__init__.py
EventBusClient/connection.py
EventBusClient/constants.py
EventBusClient/event_bus_client.py
EventBusClient/plugin_loader.py
EventBusClient/publisher.py
EventBusClient/qlogger.py
EventBusClient/rendezvous.py
EventBusClient/startup_policy.py
EventBusClient/subscriber.py
EventBusClient/subscription_cache.py
EventBusClient/utils.py
EventBusClient/version.py
EventBusClient/wait_mode.py
EventBusClient/config/config.jsonp
EventBusClient/config/config.jsonp.template
EventBusClient/examples/basic_async_producer_consumer_sample.py
EventBusClient/examples/basic_sync_producer_consumer_sample.py
EventBusClient/exchange_handler/__init__.py
EventBusClient/exchange_handler/base.py
EventBusClient/exchange_handler/fanout_handler.py
EventBusClient/exchange_handler/topic_handler.py
EventBusClient/exchange_handler/x_rtopic_handler.py
EventBusClient/message/__init__.py
EventBusClient/message/base_message.py
EventBusClient/message/basic_message.py
EventBusClient/message/control_message.py
EventBusClient/message/dict_message.py
EventBusClient/message/deprecated/__init__.py
EventBusClient/message/deprecated/std_msgs/__init__.py
EventBusClient/message/deprecated/std_msgs/dict_msg.py
EventBusClient/message/deprecated/std_msgs/float32_msg.py
EventBusClient/message/deprecated/std_msgs/float64_msg.py
EventBusClient/message/deprecated/std_msgs/header.py
EventBusClient/message/deprecated/std_msgs/int32_msg.py
EventBusClient/message/deprecated/std_msgs/msg.py
EventBusClient/message/deprecated/std_msgs/string_msg.py
EventBusClient/message/deprecated/std_msgs/uint32_msg.py
EventBusClient/message/deprecated/taf_msgs/__init__.py
EventBusClient/message/deprecated/taf_msgs/listener_event_indexer.py
EventBusClient/message/deprecated/taf_msgs/listener_event_msg.py
EventBusClient/plugins/readme.txt
EventBusClient/serializer/__init__.py
EventBusClient/serializer/base_serializer.py
EventBusClient/serializer/json_serializer.py
eventbusclient-0.1.2.dist-info/licenses/LICENSE
eventbusclient-0.1.2.dist-info/METADATA
eventbusclient-0.1.2.dist-info/WHEEL
eventbusclient-0.1.2.dist-info/top_level.txt
eventbusclient-0.1.2.dist-info/RECORD
