Metadata-Version: 2.4
Name: EventBusClient
Version: 0.1.2
Summary: An IPC message-bus based on RabbitMQ message broker
Home-page: https://github.com/test-fullautomation/python-rabbitmq-messagebus
Author: Nguyen Huynh Tri Cuong
Author-email: Cuong.NguyenHuynhTri@vn.bosch.com
Classifier: Programming Language :: Python :: 3
Classifier: License :: OSI Approved :: Apache Software License
Classifier: Operating System :: OS Independent
Classifier: Development Status :: 4 - Beta
Classifier: Intended Audience :: Developers
Classifier: Topic :: Software Development
Requires-Python: >=3.0
License-File: LICENSE
Requires-Dist: pydotdict
Dynamic: author
Dynamic: author-email
Dynamic: classifier
Dynamic: description
Dynamic: description-content-type
Dynamic: home-page
Dynamic: license-file
Dynamic: requires-dist
Dynamic: requires-python
Dynamic: summary
